MANIFEST.in
README.rst
setup.py
django_extjs4.egg-info/PKG-INFO
django_extjs4.egg-info/SOURCES.txt
django_extjs4.egg-info/dependency_links.txt
django_extjs4.egg-info/not-zip-safe
django_extjs4.egg-info/requires.txt
django_extjs4.egg-info/top_level.txt
extjs4/__init__.py
extjs4/context_processors.py
extjs4/models.py
extjs4/views.py
extjs4/static/extjs4/bootstrap.js
extjs4/static/extjs4/ext-all-debug-w-comments.js
extjs4/static/extjs4/ext-all-debug.js
extjs4/static/extjs4/ext-all-dev.js
extjs4/static/extjs4/ext-all.js
extjs4/static/extjs4/ext-debug-w-comments.js
extjs4/static/extjs4/ext-debug.js
extjs4/static/extjs4/ext-dev.js
extjs4/static/extjs4/ext-neptune-debug-w-comments.js
extjs4/static/extjs4/ext-neptune-debug.js
extjs4/static/extjs4/ext-neptune.js
extjs4/static/extjs4/ext.js
extjs4/static/extjs4/index.html
extjs4/static/extjs4/license.txt
extjs4/static/extjs4/release-notes.html
extjs4/static/extjs4/build/sdk.jsb3
extjs4/static/extjs4/builds/ext-all-sandbox-debug-w-comments.js
extjs4/static/extjs4/builds/ext-all-sandbox-debug.js
extjs4/static/extjs4/builds/ext-all-sandbox-dev.js
extjs4/static/extjs4/builds/ext-all-sandbox.js
extjs4/static/extjs4/builds/ext-core-debug-w-comments.js
extjs4/static/extjs4/builds/ext-core-debug.js
extjs4/static/extjs4/builds/ext-core-dev.js
extjs4/static/extjs4/builds/ext-core.js
extjs4/static/extjs4/builds/ext-foundation-debug-w-comments.js
extjs4/static/extjs4/builds/ext-foundation-debug.js
extjs4/static/extjs4/builds/ext-foundation-dev.js
extjs4/static/extjs4/builds/ext-foundation.js
extjs4/static/extjs4/locale/ext-lang-af.js
extjs4/static/extjs4/locale/ext-lang-bg.js
extjs4/static/extjs4/locale/ext-lang-ca.js
extjs4/static/extjs4/locale/ext-lang-cs.js
extjs4/static/extjs4/locale/ext-lang-da.js
extjs4/static/extjs4/locale/ext-lang-de.js
extjs4/static/extjs4/locale/ext-lang-el_GR.js
extjs4/static/extjs4/locale/ext-lang-en.js
extjs4/static/extjs4/locale/ext-lang-en_GB.js
extjs4/static/extjs4/locale/ext-lang-es.js
extjs4/static/extjs4/locale/ext-lang-et.js
extjs4/static/extjs4/locale/ext-lang-fa.js
extjs4/static/extjs4/locale/ext-lang-fi.js
extjs4/static/extjs4/locale/ext-lang-fr.js
extjs4/static/extjs4/locale/ext-lang-fr_CA.js
