Metadata-Version: 1.1
Name: django-extjs4
Version: 1.1.3-extjs4.1.1
Summary: Packages extjs4 as a Django app.
Home-page: http://github.com/espenak/django_extjs4
Author: Espen Angell Kristiansen
Author-email: UNKNOWN
License: GPL
Platform: UNKNOWN
Classifier: Development Status :: 5 - Production/Stable
Classifier: Environment :: Web Environment
Classifier: Framework :: Django
Classifier: Intended Audience :: Developers
Classifier: License :: OSI Approved
Classifier: Operating System :: OS Independent
Classifier: Programming Language :: Python
